packaging/__init__.py
packaging/bdist_trinoadmin.py
trino_admin-2.16.dist-info/DESCRIPTION.rst
trino_admin-2.16.dist-info/METADATA
trino_admin-2.16.dist-info/RECORD
trino_admin-2.16.dist-info/WHEEL
trino_admin-2.16.dist-info/entry_points.txt
trino_admin-2.16.dist-info/metadata.json
trino_admin-2.16.dist-info/top_level.txt
trinoadmin/__init__.py
trinoadmin/_version.py
trinoadmin/catalog.py
trinoadmin/collect.py
trinoadmin/config.py
trinoadmin/configure_cmds.py
trinoadmin/coordinator.py
trinoadmin/deploy.py
trinoadmin/fabric_patches.py
trinoadmin/file.py
trinoadmin/main.py
trinoadmin/mode.py
trinoadmin/node.py
trinoadmin/package.py
trinoadmin/plugin.py
trinoadmin/server.py
trinoadmin/topology.py
trinoadmin/trino-admin-logging.ini
trinoadmin/trino_conf.py
trinoadmin/trinoclient.py
trinoadmin/workers.py
trinoadmin/standalone/__init__.py
trinoadmin/standalone/config.py
trinoadmin/util/__init__.py
trinoadmin/util/all_write_handler.py
trinoadmin/util/application.py
trinoadmin/util/base_config.py
trinoadmin/util/constants.py
trinoadmin/util/exception.py
trinoadmin/util/fabric_application.py
trinoadmin/util/fabricapi.py
trinoadmin/util/filesystem.py
trinoadmin/util/hiddenoptgroup.py
trinoadmin/util/httpscacertconnection.py
trinoadmin/util/local_config_util.py
trinoadmin/util/parser.py
trinoadmin/util/remote_config_util.py
trinoadmin/util/trino_config.py
trinoadmin/util/validators.py
trinoadmin/util/version_util.py
trinoadmin/yarn_slider/__init__.py
trinoadmin/yarn_slider/config.py
trinoadmin/yarn_slider/server.py
trinoadmin/yarn_slider/slider.py
util/__init__.py
util/http.py
util/semantic_version.py
