Metadata-Version: 2.0
Name: trino-admin
Version: 2.16
Summary: Trino-admin installs, configures, and manages Trino/Presto installations.
Home-page: https://github.com/wgzhao/trino-admin
Author: wgzhao
Author-email: UNKNOWN
License: APLv2
Keywords: trino-admin
Platform: UNKNOWN
Classifier: Development Status :: 4 - Beta
Classifier: Intended Audience :: Developers
Classifier: License :: OSI Approved :: Apache Software License
Classifier: Natural Language :: English
Classifier: Programming Language :: Python :: 2
Classifier: Programming Language :: Python :: 2.7
Requires-Dist: Fabric (==1.14.1)
Requires-Dist: argparse (==1.4.0)
Requires-Dist: bcrypt (==3.1.3)
Requires-Dist: cffi (==1.15.0)
Requires-Dist: cryptography (==2.6)
Requires-Dist: flake8 (==3.9.2)
Requires-Dist: overrides (==2.8.0)
Requires-Dist: paramiko (==2.7.2)
Requires-Dist: pip (==20.3.4)
Requires-Dist: pycparser (==2.20)
Requires-Dist: pyjks (==20.0.0)
Requires-Dist: pyjwt (==1.7.1)
Requires-Dist: requests (==2.26.0)
Requires-Dist: retrying (==1.3.3)
Requires-Dist: setuptools (==42.0.2)
Requires-Dist: wheel (==0.36.2)
